{
  "name": "event-debugger",
  "repo": "matthewmueller/event-debugger",
  "description": "step through events!",
  "version": "0.0.2",
  "keywords": [],
  "dependencies": {
    "matthewmueller/event-spy": "*",
    "component/domify": "*",
    "component/event": "*",
    "component/classes": "*",
    "component/reactive": "*",
    "matthewmueller/print-element": "*"
  },
  "development": {},
  "license": "MIT",
  "main": "index.js",
  "scripts": [
    "index.js",
    "template.js"
  ],
  "styles": [
    "event-debugger.css"
  ]
}
